bias/__init__.py
bias/set_est.py
bias/shapley.py
bias/test/__init__.py
bias/test/set_est.py
bias-0.0.1.dist-info/LICENSE
bias-0.0.1.dist-info/METADATA
bias-0.0.1.dist-info/WHEEL
bias-0.0.1.dist-info/top_level.txt
bias-0.0.1.dist-info/RECORD
