Metadata-Version: 2.1
Name: bias
Version: 0.0.1
Summary: tools to track statistical bias
Home-page: https://github.com/thorwhalen/ut/tree/master/stats/bin_est/bias
Author: Thor Whalen
License: mit
Keywords: statistics,bias
Platform: any
